src/pngcoder.py
src/wavcoder.py
pngcoder-1.3.dist-info/LICENSE.txt
pngcoder-1.3.dist-info/METADATA
pngcoder-1.3.dist-info/WHEEL
pngcoder-1.3.dist-info/entry_points.txt
pngcoder-1.3.dist-info/top_level.txt
pngcoder-1.3.dist-info/RECORD
