Metadata-Version: 2.1
Name: pngcoder
Version: 1.3
Summary: Encode (obfuscate) any file to PNG or WAV and vise versa
Home-page: https://github.com/jencat42/pngcoder
Author: JenCat
Author-email: jencat@ex.ua
License: MIT
Keywords: obfuscate obfuscator encode encoder png wav binary
Platform: UNKNOWN
Classifier: Development Status :: 4 - Beta
Classifier: Intended Audience :: End Users/Desktop
Classifier: Topic :: Utilities
Classifier: License :: OSI Approved :: MIT License
Classifier: Programming Language :: Python :: 3
Requires-Python: >=3.7
Requires-Dist: Pillow
